deepface/DeepFace.py
deepface/__init__.py
deepface/basemodels/ArcFace.py
deepface/basemodels/Boosting.py
deepface/basemodels/DeepID.py
deepface/basemodels/DlibResNet.py
deepface/basemodels/DlibWrapper.py
deepface/basemodels/Facenet.py
deepface/basemodels/Facenet512.py
deepface/basemodels/FbDeepFace.py
deepface/basemodels/OpenFace.py
deepface/basemodels/VGGFace.py
deepface/basemodels/__init__.py
deepface/commons/__init__.py
deepface/commons/distance.py
deepface/commons/functions.py
deepface/commons/realtime.py
deepface/detectors/DlibWrapper.py
deepface/detectors/FaceDetector.py
deepface/detectors/MediapipeWrapper.py
deepface/detectors/MtcnnWrapper.py
deepface/detectors/OpenCvWrapper.py
deepface/detectors/RetinaFaceWrapper.py
deepface/detectors/SsdWrapper.py
deepface/detectors/__init__.py
deepface/extendedmodels/Age.py
deepface/extendedmodels/Emotion.py
deepface/extendedmodels/Gender.py
deepface/extendedmodels/Race.py
deepface/extendedmodels/__init__.py
deepface/models/__init__.py
nvface-0.1.0.data/scripts/face-recognition-ensemble-model.txt
nvface-0.1.0.dist-info/LICENSE
nvface-0.1.0.dist-info/METADATA
nvface-0.1.0.dist-info/WHEEL
nvface-0.1.0.dist-info/top_level.txt
nvface-0.1.0.dist-info/RECORD
