Metadata-Version: 2.1
Name: nvface
Version: 0.1.0
Summary: Forked Lightweight Face Recognition and Facial Attribute Analysis Framework (Age, Gender, Emotion, Race) for Python
Home-page: https://github.com/serengil/deepface
Author: Lavrenkov
Author-email: lavrenkovnv@gmail.com
License: UNKNOWN
Platform: UNKNOWN
Classifier: Programming Language :: Python :: 3
Classifier: License :: OSI Approved :: MIT License
Classifier: Operating System :: OS Independent
Requires-Python: >=3.5.5
Requires-Dist: Flask (>=1.1.2)
Requires-Dist: Pillow (>=5.2.0)
Requires-Dist: gdown (>=3.10.1)
Requires-Dist: keras (>=2.2.0)
Requires-Dist: mtcnn (>=0.1.0)
Requires-Dist: numpy (>=1.14.0)
Requires-Dist: opencv-python (>=3.4.4)
Requires-Dist: pandas (>=0.23.4)
Requires-Dist: retina-face (>=0.0.1)
Requires-Dist: tensorflow (>=1.9.0)
Requires-Dist: tqdm (>=4.30.0)
